koji_wrapper/__init__.py
koji_wrapper/base.py
koji_wrapper/exceptions.py
koji_wrapper/tag.py
koji_wrapper/util.py
koji_wrapper/validators.py
koji_wrapper/wrapper.py
koji_wrapper/test_support/__init__.py
koji_wrapper/test_support/sample_data.py
koji_wrapper-0.4.0.dist-info/LICENSE
koji_wrapper-0.4.0.dist-info/METADATA
koji_wrapper-0.4.0.dist-info/WHEEL
koji_wrapper-0.4.0.dist-info/top_level.txt
koji_wrapper-0.4.0.dist-info/RECORD
