Metadata-Version: 2.1
Name: koji_wrapper
Version: 0.4.0
Summary: """
Home-page: https://github.com/release-depot/koji_wrapper
Author: Jason Guiditta
Author-email: jason.guiditta@gmail.com
License: MIT
Project-URL: Bug Tracker, https://github.com/release-depot/koji_wrapper/issues
Keywords: koji_wrapper
Classifier: Development Status :: 3 - Alpha
Classifier: Intended Audience :: Developers
Classifier: License :: OSI Approved :: MIT License
Classifier: Natural Language :: English
Classifier: Programming Language :: Python :: 3
License-File: LICENSE
Requires-Dist: koji
Requires-Dist: toolchest
Provides-Extra: dist
Requires-Dist: build; extra == "dist"
Requires-Dist: setuptools-scm; extra == "dist"
Requires-Dist: twine; extra == "dist"
Provides-Extra: docs
Requires-Dist: sphinx==4.1.2; extra == "docs"
Requires-Dist: sphinx-autobuild==2021.3.14; extra == "docs"
Requires-Dist: sphinx-rtd-theme==0.5.2; extra == "docs"
Provides-Extra: test
Requires-Dist: flake8; extra == "test"
Requires-Dist: pytest; extra == "test"
Requires-Dist: pytest-cov; extra == "test"
Requires-Dist: pytest-datadir; extra == "test"
Requires-Dist: tox; extra == "test"
